CHANGELOG.txt
LICENSE.txt
MANIFEST.in
README.rst
VERSION.txt
apptimize.py
setup.cfg
setup.py
Apptimize.egg-info/PKG-INFO
Apptimize.egg-info/SOURCES.txt
Apptimize.egg-info/dependency_links.txt
Apptimize.egg-info/requires.txt
Apptimize.egg-info/top_level.txt