Metadata-Version: 2.1
Name: Apptimize
Version: 1.2.44
Summary: Apptimize Python Server SDK
Home-page: https://apptimize.com/
Author: Apptimize, Inc.
Author-email: support@apptimize.com
License: UNKNOWN
Project-URL: Learn More, https://apptimize.com/
Project-URL: Documentation, https://apptimize.com/docs/
Keywords: apptimize testing ab experimentation optimize
Platform: UNKNOWN
Classifier: Development Status :: 3 - Alpha
Classifier: Intended Audience :: Developers
Classifier: Topic :: Software Development :: Testing
Classifier: License :: Other/Proprietary License
Classifier: Programming Language :: Python :: 3
Requires-Python: >=3.5.1
